CockpitCP-1.0.0.data/scripts/cockpit-ipc
CockpitCP-1.0.0.data/scripts/cockpit-panel
CockpitCP-1.0.0.data/scripts/cockpit-ssl-gen
cockpit/__init__.py
etc/cockpit/config.json
etc/init.d/cockpit
var/lib/cockpit/plugins/.placeholder
CockpitCP-1.0.0.dist-info/METADATA
CockpitCP-1.0.0.dist-info/WHEEL
CockpitCP-1.0.0.dist-info/top_level.txt
CockpitCP-1.0.0.dist-info/RECORD
