Metadata-Version: 2.1
Name: CockpitCP
Version: 1.0.0
Summary: The server administration panel
Home-page: http://taiosolve.xyz/
Author: Taiosolve
Author-email: support@taiosolve.xyz
License: UNKNOWN
Platform: UNKNOWN
